README.rst
setup.py
websigning/__init__.py
websigning/backend.py
websigning/utils.py
websigning/validators.py
websigning.egg-info/PKG-INFO
websigning.egg-info/SOURCES.txt
websigning.egg-info/dependency_links.txt
websigning.egg-info/entry_points.txt
websigning.egg-info/not-zip-safe
websigning.egg-info/requires.txt
websigning.egg-info/top_level.txt
websigning/credentials/__init__.py
websigning/credentials/base.py
websigning/credentials/ephemeral.py
websigning/credentials/jwsplat.py
websigning/credentials/smime.py
websigning/sign/__init__.py
websigning/sign/base.py
websigning/sign/receipts.py
websigning/sign/xpi.py
websigning/tests/__init__.py
websigning/tests/base.py
websigning/tests/data.py
websigning/tests/test_addons.py
websigning/tests/test_receipts.py
websigning/tests/test_xpi.py