Metadata-Version: 1.0
Name: websigning
Version: 0.1
Summary: Application receipt certifier and verifier
Home-page: http://mozilla.org
Author: Ryan Tilder
Author-email: services-dev@mozilla.com
License: UNKNOWN
Keywords: web services
Platform: UNKNOWN
Classifier: Programming Language :: Python
